deeps/__init__.py
deeps/cli.py
deeps/main.py
deeps/model_torch.py
deeps/utils.py
deeps_cibr-1.0.dist-info/METADATA
deeps_cibr-1.0.dist-info/WHEEL
deeps_cibr-1.0.dist-info/entry_points.txt
deeps_cibr-1.0.dist-info/top_level.txt
deeps_cibr-1.0.dist-info/RECORD
