Metadata-Version: 2.1
Name: deeps-cibr
Version: 1.0
Summary: A deeps inference module.
Home-page: UNKNOWN
Author: azzhu
Author-email: zhu.qingjie@qq.com
License: MIT
Platform: UNKNOWN
Classifier: Programming Language :: Python :: 3
Classifier: License :: OSI Approved :: MIT License
Classifier: Operating System :: OS Independent
Requires-Python: >=3
Requires-Dist: numpy
Requires-Dist: opencv-python
Requires-Dist: torch
Requires-Dist: requests
Requires-Dist: PyYAML
